parrotai/__init__.py
parrotai/parrotai.py
parrotai-0.1.18.dist-info/METADATA
parrotai-0.1.18.dist-info/WHEEL
parrotai-0.1.18.dist-info/top_level.txt
parrotai-0.1.18.dist-info/RECORD
