Metadata-Version: 2.1
Name: parrotai
Version: 0.1.18
Summary: API for Parrot AI - a decentralized AI.
Author: Andy Tran
Author-email: andy@joinparrot.ai
Classifier: Programming Language :: Python :: 3
Classifier: License :: OSI Approved :: Apache Software License
Classifier: Operating System :: OS Independent
Requires-Python: >=3.6
